fruit/__init__.py
fruit/api.py
fruit/cli.py
fruit/auth/__init__.py
fruit/auth/bin_io.py
fruit/auth/pure_eddsa.py
fruit/auth/signify_key.py
fruit/auth/ssh_agent.py
fruit/auth/ssh_key.py
fruit/auth/token_tool.py
fruit_cli-0.8.1.data/scripts/fruit-cli
fruit_cli-0.8.1.dist-info/LICENSE.txt
fruit_cli-0.8.1.dist-info/METADATA
fruit_cli-0.8.1.dist-info/WHEEL
fruit_cli-0.8.1.dist-info/top_level.txt
fruit_cli-0.8.1.dist-info/RECORD
