Metadata-Version: 2.1
Name: fruit-cli
Version: 0.8.1
Summary: Command-line application plus API client for FRμIT cluster management
Home-page: https://github.com/fruit-testbed/fruit-cli/
Author: FRμIT Developers
Author-email: tony.garnock-jones@glasgow.ac.uk
License: Creative Commons Attribution-ShareAlike 4.0 International Public
Keywords: fruit-cli
Platform: any
Classifier: Development Status :: 3 - Alpha
Classifier: Intended Audience :: Developers
Classifier: Topic :: Software Development :: Libraries :: Python Modules
Classifier: License :: Other/Proprietary License
Classifier: Programming Language :: Python :: 2
Classifier: Programming Language :: Python :: 2.7
Classifier: Programming Language :: Python :: 3
Classifier: Programming Language :: Python :: 3.3
Classifier: Programming Language :: Python :: 3.4
Classifier: Programming Language :: Python :: 3.5
Classifier: Programming Language :: Python :: 3.6
Requires-Python: >=2.7, <4
Requires-Dist: requests
Requires-Dist: PyYAML
Requires-Dist: future
Requires-Dist: py-bcrypt
Requires-Dist: cryptography
